pyxl320/DummySerial.py
pyxl320/Packet.py
pyxl320/ServoSerial.py
pyxl320/__init__.py
pyxl320/utils.py
pyxl320/version.py
pyxl320/xl320.py
pyxl320-0.10.0.data/scripts/get_angle.py
pyxl320-0.10.0.data/scripts/servo_ping.py
pyxl320-0.10.0.data/scripts/servo_reboot.py
pyxl320-0.10.0.data/scripts/servo_reset.py
pyxl320-0.10.0.data/scripts/set_angle.py
pyxl320-0.10.0.data/scripts/set_baud_rate.py
pyxl320-0.10.0.data/scripts/set_id.py
pyxl320-0.10.0.dist-info/DESCRIPTION.rst
pyxl320-0.10.0.dist-info/METADATA
pyxl320-0.10.0.dist-info/RECORD
pyxl320-0.10.0.dist-info/WHEEL
pyxl320-0.10.0.dist-info/metadata.json
pyxl320-0.10.0.dist-info/top_level.txt
