Metadata-Version: 2.0
Name: pyxl320
Version: 0.10.0
Summary: A library to control dynamixel XL-320 servos with python
Home-page: http://github.com/walchko/pyxl320
Author: Kevin Walchko
Author-email: walchko@users.noreply.github.com
License: MIT
Keywords: dynamixel,xl320,xl-320,servo,actuator,library,robotics,robot,smart,spider
Platform: UNKNOWN
Classifier: Development Status :: 4 - Beta
Classifier: Intended Audience :: Developers
Classifier: License :: OSI Approved :: MIT License
Classifier: Operating System :: OS Independent
Classifier: Programming Language :: Python :: 2.7
Classifier: Programming Language :: Python :: 3.6
Classifier: Topic :: Software Development :: Libraries
Classifier: Topic :: Software Development :: Libraries :: Python Modules
Classifier: Topic :: Software Development :: Libraries :: Application Frameworks
Requires-Dist: pyserial
Requires-Dist: simplejson
Requires-Dist: build-utils
